fights/__init__.py
fights/base.py
fights/envs/__init__.py
fights/envs/othello.py
fights/envs/othello_cythonfn.c
fights/envs/othello_cythonfn.cp37-win_amd64.pyd
fights/envs/othello_cythonfn.pyi
fights/envs/othello_cythonfn.pyx
fights/envs/puoribor.py
fights/envs/puoribor_cython.c
fights/envs/puoribor_cython.cp37-win_amd64.pyd
fights/envs/puoribor_cython.pyi
fights/envs/puoribor_cython.pyx
fights/envs/quoridor.py
fights/envs/quoridor_cython.c
fights/envs/quoridor_cython.cp37-win_amd64.pyd
fights/envs/quoridor_cython.pyi
fights/envs/quoridor_cython.pyx
fights-0.9.0.dist-info/LICENSE.txt
fights-0.9.0.dist-info/METADATA
fights-0.9.0.dist-info/WHEEL
fights-0.9.0.dist-info/top_level.txt
fights-0.9.0.dist-info/RECORD
