Metadata-Version: 2.1
Name: fights
Version: 0.9.0
Summary: Competitive artificial intelligence battle environments
Author-email: "PoApper, Inc." <support@poapper.com>
Maintainer: Taemin Lee
Maintainer-email: Lucas Yunkyu Lee <me@luc.li>, Ryang Sohn <loop.infinitely@gmail.com>
License: MIT License
Project-URL: documentation, https://fights.readthedocs.io
Project-URL: repository, https://github.com/poapper-inc/fights
Classifier: License :: OSI Approved :: MIT License
Classifier: Programming Language :: Python :: 3
Classifier: Programming Language :: Python :: 3 :: Only
Classifier: Programming Language :: Python :: 3.7
Classifier: Programming Language :: Python :: 3.8
Classifier: Programming Language :: Python :: 3.9
Classifier: Programming Language :: Python :: 3.10
Classifier: Programming Language :: Python :: 3.11
Requires-Python: >=3.7
License-File: LICENSE.txt
